{
  "run_time": "2026-04-10 13:20:14",
  "story_count": 7,
  "stories": [
    {
      "link": "https://apple.news/ApwUuXzY7Qy2SU0KKRKaw5w",
      "rank": 1,
      "section": "top",
      "run_time": "2026-04-10 13:20:14",
      "pub_time": "",
      "publication": "The Guardian",
      "author": "",
      "headline": "U.S. inflation soars in March as war with Iran drives economy into uncertainty",
      "article_headline": "U.S. inflation soars in March as war with Iran drives economy into uncertainty"
    },
    {
      "link": "https://apple.news/AHDr1PJjqSCqJvo15ZWS1Aw",
      "rank": 2,
      "section": "top",
      "run_time": "2026-04-10 13:20:14",
      "pub_time": "2026-04-10 13:13:43",
      "publication": "Bloomberg",
      "author": "Dana Khraiche and Dan Williams",
      "headline": "Why the Lebanon conflict complicates resolution of the Iran war",
      "article_headline": "Why the Lebanon conflict complicates resolution of the Iran war"
    },
    {
      "link": "https://apple.news/AHDr1PJjqSCqJvo15ZWS1Aw",
      "rank": 3,
      "section": "top",
      "run_time": "2026-04-10 13:20:14",
      "pub_time": "2026-04-10 13:13:15",
      "publication": "Bloomberg",
      "author": "Dana Khraiche and Dan Williams",
      "headline": "Why the Lebanon conflict complicates resolution of the Iran war",
      "article_headline": "Why the Lebanon conflict complicates resolution of the Iran war"
    },
    {
      "link": "",
      "rank": "plus",
      "section": "top",
      "run_time": "2026-04-10 13:20:14",
      "pub_time": "",
      "publication": "The Washington Post",
      "author": "",
      "headline": "Trump officials unveil designs for president’s controversial 250-foot arch",
      "article_headline": "",
      "link_status": "P"
    },
    {
      "link": "https://apple.news/AHWFeZKmRSAKOwt-HHqGDrg",
      "rank": 4,
      "section": "top",
      "run_time": "2026-04-10 13:20:14",
      "pub_time": "2026-04-10 13:13:43",
      "publication": "NBC News",
      "author": "Janis Mackey Frayer",
      "headline": "China’s Xi Jinping talks peace with Taiwan’s opposition leader even as Beijing raises military pressure",
      "article_headline": "China’s Xi Jinping talks peace with Taiwan’s opposition leader even as Beijing raises military pressure"
    },
    {
      "link": "https://apple.news/AHWFeZKmRSAKOwt-HHqGDrg",
      "rank": 5,
      "section": "top",
      "run_time": "2026-04-10 13:20:14",
      "pub_time": "2026-04-10 13:13:16",
      "publication": "NBC News",
      "author": "Janis Mackey Frayer",
      "headline": "China’s Xi Jinping talks peace with Taiwan’s opposition leader even as Beijing raises military pressure",
      "article_headline": "China’s Xi Jinping talks peace with Taiwan’s opposition leader even as Beijing raises military pressure"
    },
    {
      "link": "https://apple.news/AQddhB_P8SAGf9ojeNwyfXg",
      "rank": 6,
      "section": "top",
      "run_time": "2026-04-10 13:20:14",
      "pub_time": "",
      "publication": "Video",
      "author": "",
      "headline": "CBS News, As Artemis II heads back to Earth, the astronauts are staking their lives on the heat shield",
      "article_headline": "As Artemis II heads back to Earth, the astronauts are staking their lives on the heat shield"
    }
  ]
}