{
  "run_time": "2026-03-12 08:10:13",
  "story_count": 17,
  "stories": [
    {
      "link": "https://apple.news/A0FxPdlUjRBKL2gtN3AiKVw",
      "rank": 1,
      "section": "top",
      "run_time": "2026-03-12 08:10:13",
      "pub_time": "2026-03-12 07:31:15",
      "publication": "The Associated Press",
      "headline": "Iran’s attacks on Middle East shipping and energy infrastructure send oil prices up again",
      "article_headline": "Iran’s attacks on Middle East shipping and energy infrastructure send oil prices up again"
    },
    {
      "link": "https://apple.news/AxxtHMbjwT2OfZi-Xn2jDEA",
      "rank": 2,
      "section": "top",
      "run_time": "2026-03-12 08:10:13",
      "pub_time": "",
      "publication": "NBC News",
      "headline": "Trump launches new tariff-related investigations of key trade partners",
      "article_headline": "Trump launches new tariff-related investigations of key trade partners"
    },
    {
      "link": "https://apple.news/AgPW6-8jBQe-LqHtPbLTpxQ",
      "rank": 3,
      "section": "top",
      "run_time": "2026-03-12 08:10:13",
      "pub_time": "2026-03-12 07:31:16",
      "publication": "The Washington Post",
      "headline": "Why it’s easier and cheaper for you to buy GLP-1s",
      "article_headline": "Why it’s easier and cheaper for you to buy GLP-1s"
    },
    {
      "link": "https://apple.news/AFCy7s3qtSo-w-3Psly62vQ",
      "rank": 4,
      "section": "top",
      "run_time": "2026-03-12 08:10:13",
      "pub_time": "",
      "publication": "NPR",
      "headline": "The crackdown on immigrant truckers shifts into higher gear",
      "article_headline": "The crackdown on immigrant truckers shifts into higher gear"
    },
    {
      "link": "https://apple.news/AgPW6-8jBQe-LqHtPbLTpxQ",
      "rank": 5,
      "section": "top",
      "run_time": "2026-03-12 08:10:13",
      "pub_time": "2026-03-12 07:31:16",
      "publication": "The Washington Post",
      "headline": "Why it’s easier and cheaper for you to buy GLP-1s",
      "article_headline": "Why it’s easier and cheaper for you to buy GLP-1s"
    },
    {
      "link": "",
      "rank": "plus",
      "section": "top",
      "run_time": "2026-03-12 08:10:13",
      "pub_time": "2026-03-12 07:31:44",
      "publication": "Los Angeles Times",
      "headline": "They lost their Oscar trophies in the wildfires. So what happens next?",
      "article_headline": ""
    },
    {
      "link": "",
      "rank": "plus",
      "section": "top",
      "run_time": "2026-03-12 08:10:13",
      "pub_time": "2026-03-12 07:31:57",
      "publication": "The Wall Street Journal",
      "headline": "The billion-dollar AI startup that was founded by teenagers",
      "article_headline": ""
    },
    {
      "link": "",
      "rank": "plus",
      "section": "top",
      "run_time": "2026-03-12 08:10:13",
      "pub_time": "2026-03-12 07:31:17",
      "publication": "Los Angeles Times",
      "headline": "They lost their Oscar trophies in the wildfires. So what happens next?",
      "article_headline": ""
    },
    {
      "link": "",
      "rank": "plus",
      "section": "top",
      "run_time": "2026-03-12 08:10:13",
      "pub_time": "2026-03-12 07:31:30",
      "publication": "The Wall Street Journal",
      "headline": "The billion-dollar AI startup that was founded by teenagers",
      "article_headline": ""
    },
    {
      "link": "https://apple.news/Ac1TiB1r5RkO3I1liwfHnaw",
      "rank": "audio",
      "section": "top",
      "run_time": "2026-03-12 08:10:13",
      "pub_time": "",
      "publication": "Apple News Today",
      "headline": "Countries turn to emergency oil supplies. It won’t buy much time.",
      "article_headline": ""
    },
    {
      "link": "https://apple.news/Ac1TiB1r5RkO3I1liwfHnaw",
      "rank": "audio",
      "section": "top",
      "run_time": "2026-03-12 08:10:13",
      "pub_time": "",
      "publication": "Apple News Today",
      "headline": "Countries turn to emergency oil supplies. It won’t buy much time.",
      "article_headline": ""
    },
    {
      "link": "",
      "rank": "plus",
      "section": "top",
      "run_time": "2026-03-12 08:10:13",
      "pub_time": "2026-03-12 08:00:57",
      "publication": "Billboard",
      "headline": "Why A2IM Started an RIAA-Style Sales Certification Program for Indie Artists",
      "article_headline": ""
    },
    {
      "link": "",
      "rank": "plus",
      "section": "top",
      "run_time": "2026-03-12 08:10:13",
      "pub_time": "2026-03-12 08:00:17",
      "publication": "Los Angeles Times",
      "headline": "Hollywood's top films were less diverse in 2025: 'Studios have relapsed into a colorblind complacency'",
      "article_headline": ""
    },
    {
      "link": "",
      "rank": "plus",
      "section": "top",
      "run_time": "2026-03-12 08:10:13",
      "pub_time": "2026-02-26 08:15:37",
      "publication": "Apple News Plus",
      "headline": "National Geographic, What you’ve been told about eggs and cholesterol is wrong",
      "article_headline": ""
    },
    {
      "link": "",
      "rank": "plus",
      "section": "top",
      "run_time": "2026-03-12 08:10:13",
      "pub_time": "",
      "publication": "The Athletic",
      "headline": "Ranking the quarterfinal matchups in the World Baseball Classic",
      "article_headline": ""
    },
    {
      "link": "",
      "rank": "plus",
      "section": "top",
      "run_time": "2026-03-12 08:10:13",
      "pub_time": "2026-03-12 08:08:29",
      "publication": "Apple News Plus",
      "headline": "Houston Chronicle, Katy area will have more retail stores, restaurant options under new development",
      "article_headline": ""
    },
    {
      "link": "",
      "rank": "plus",
      "section": "top",
      "run_time": "2026-03-12 08:10:13",
      "pub_time": "",
      "publication": "Apple News Plus",
      "headline": "National Geographic History, Who really wrote the Old Testament?, Javier Alonso López",
      "article_headline": ""
    }
  ]
}