{
  "run_time": "2026-04-13 10:20:17",
  "story_count": 11,
  "stories": [
    {
      "link": "https://apple.news/ANl-UXKmrTZKKG89DVTyjdw",
      "rank": 1,
      "section": "top",
      "run_time": "2026-04-13 10:20:17",
      "pub_time": "",
      "publication": "The Wall Street Journal",
      "author": "",
      "headline": "U.S. blockade of Strait of Hormuz appears to take effect, LIVE",
      "article_headline": "U.S. Blockade of Strait of Hormuz Appears to Take Effect"
    },
    {
      "link": "https://apple.news/A33IIm-8MTv-PX4nrluGzyg",
      "rank": 2,
      "section": "top",
      "run_time": "2026-04-13 10:20:17",
      "pub_time": "",
      "publication": "ABC News",
      "author": "",
      "headline": "Congress returning from 2-week recess as Iran debate rages and members face expulsion",
      "article_headline": "Congress returning from 2-week recess as Iran debate rages and members face expulsion"
    },
    {
      "link": "https://apple.news/A1PAe1QgSTtmHPcSXa3Vfsw",
      "rank": 3,
      "section": "top",
      "run_time": "2026-04-13 10:20:17",
      "pub_time": "2026-04-13 10:16:19",
      "publication": "CBS News",
      "author": "Stefan Becket and Jacob Rosen",
      "headline": "Judge dismisses Trump’s defamation suit against Wall Street Journal over Epstein letter",
      "article_headline": "Judge dismisses Trump’s defamation suit against Wall Street Journal over Epstein letter"
    },
    {
      "link": "https://apple.news/AYG5_01M_SAWNOaov-AkAfA",
      "rank": 4,
      "section": "top",
      "run_time": "2026-04-13 10:20:17",
      "pub_time": "2026-04-13 10:16:47",
      "publication": "NBC News",
      "author": "Patrick Smith",
      "headline": "Europe celebrates as Viktor Orbán’s stunning defeat deals a blow to Putin and Trump",
      "article_headline": "Europe celebrates as Viktor Orbán’s stunning defeat deals a blow to Putin and Trump"
    },
    {
      "link": "https://apple.news/A1PAe1QgSTtmHPcSXa3Vfsw",
      "rank": 5,
      "section": "top",
      "run_time": "2026-04-13 10:20:17",
      "pub_time": "2026-04-13 10:16:20",
      "publication": "CBS News",
      "author": "Stefan Becket and Jacob Rosen",
      "headline": "Judge dismisses Trump’s defamation suit against Wall Street Journal over Epstein letter",
      "article_headline": "Judge dismisses Trump’s defamation suit against Wall Street Journal over Epstein letter"
    },
    {
      "link": "https://apple.news/AYG5_01M_SAWNOaov-AkAfA",
      "rank": 6,
      "section": "top",
      "run_time": "2026-04-13 10:20:17",
      "pub_time": "2026-04-13 10:16:48",
      "publication": "NBC News",
      "author": "Patrick Smith",
      "headline": "Europe celebrates as Viktor Orbán’s stunning defeat deals a blow to Putin and Trump",
      "article_headline": "Europe celebrates as Viktor Orbán’s stunning defeat deals a blow to Putin and Trump"
    },
    {
      "link": "https://apple.news/An3zsiKspQdS2I5Qsa_QP4g?route=aHR0cHM6Ly9hcHBsZS5uZXdzL1RoODFreUZ1UFJIV2RGUGFXT0tHWU5RI25mZl9paWQ%3D",
      "rank": 7,
      "section": "top",
      "run_time": "2026-04-13 10:20:17",
      "pub_time": "",
      "publication": "Apple News Spotlight",
      "author": "",
      "headline": "Business, The biggest IRS traps to avoid this tax season, Apple News Editors",
      "article_headline": ""
    },
    {
      "link": "https://apple.news/AVLjH71K4T_SjfWEeBlBZrA",
      "rank": 1,
      "section": "trending",
      "run_time": "2026-04-13 10:20:17",
      "pub_time": "2026-04-12 12:23:48",
      "publication": "Southern Living",
      "author": "Christine Fiorentino",
      "headline": "Why You Should Wash Bananas As Soon As You Get Home (It Matters More Than You Think)",
      "article_headline": "Why You Should Wash Bananas As Soon As You Get Home (It Matters More Than You Think)"
    },
    {
      "link": "https://apple.news/A6vqPk-U5R52qcOPO-D6_yw",
      "rank": 2,
      "section": "trending",
      "run_time": "2026-04-13 10:20:17",
      "pub_time": "2026-04-12 16:24:21",
      "publication": "BuzzFeed",
      "author": "Jake Farrington",
      "headline": "\"Nobody Else Comes Close To The US In This Regard\": 32 Things That The United States Does Really, Really, Reeeeeally Well, And They Might Just Restore A Little Bit Of Faith In This Country",
      "article_headline": "\"Nobody Else Comes Close To The US In This Regard\": 32 Things That The United States Does Really, Really, Reeeeeally Well, And They Might Just Restore A Little Bit Of Faith In This Country"
    },
    {
      "link": "",
      "rank": 3,
      "section": "trending",
      "run_time": "2026-04-13 10:20:17",
      "pub_time": "2026-04-12 10:24:48",
      "publication": "",
      "author": "Stacey Leasca",
      "headline": "This Is One of the Best Places to Retire in the U.S. for Low Taxes, Mental Health, and Quality of Life",
      "article_headline": "",
      "link_status": "P"
    },
    {
      "link": "https://apple.news/AC15b2CCwTkexszWqFygnww",
      "rank": 4,
      "section": "trending",
      "run_time": "2026-04-13 10:20:17",
      "pub_time": "2026-04-13 08:24:48",
      "publication": "Popular Mechanics",
      "author": "Darren Orf",
      "headline": "Scientists Just Created Super-Strong Steel That Never Rusts. It'll Change Manufacturing.",
      "article_headline": "Scientists Just Created Super-Strong Steel That Never Rusts. It'll Change Manufacturing."
    }
  ]
}