{
  "run_time": "2026-04-06 13:20:15",
  "story_count": 7,
  "stories": [
    {
      "link": "https://apple.news/An3FzN2ctTcaUDYCNcDij0g",
      "rank": 1,
      "section": "top",
      "run_time": "2026-04-06 13:20:15",
      "pub_time": "",
      "publication": "The Associated Press",
      "author": "",
      "headline": "Artemis II breaks Apollo 13’s distance record as humans travel farther from Earth than ever before",
      "article_headline": "Artemis II breaks Apollo 13’s distance record as humans travel farther from Earth than ever before"
    },
    {
      "link": "https://apple.news/AseMBTWblTDORjQFEDBu0Mg",
      "rank": 2,
      "section": "top",
      "run_time": "2026-04-06 13:20:15",
      "pub_time": "2026-04-06 13:16:44",
      "publication": "Bloomberg",
      "author": "Hadriana Lowenkron and Eltaf Najafizada",
      "headline": "Trump amps threat to “take out” Iran before Tuesday deadline",
      "article_headline": "Trump amps threat to “take out” Iran before Tuesday deadline"
    },
    {
      "link": "https://apple.news/AseMBTWblTDORjQFEDBu0Mg",
      "rank": 3,
      "section": "top",
      "run_time": "2026-04-06 13:20:15",
      "pub_time": "2026-04-06 13:16:17",
      "publication": "Bloomberg",
      "author": "Hadriana Lowenkron and Eltaf Najafizada",
      "headline": "Trump amps threat to “take out” Iran before Tuesday deadline",
      "article_headline": "Trump amps threat to “take out” Iran before Tuesday deadline"
    },
    {
      "link": "https://apple.news/AGswrhMtMTT2D94GPGymGSg",
      "rank": 4,
      "section": "top",
      "run_time": "2026-04-06 13:20:15",
      "pub_time": "",
      "publication": "Reuters",
      "author": "",
      "headline": "Supreme Court clears way for dismissal of case against Trump ally Steve Bannon",
      "article_headline": "Supreme Court clears way for dismissal of case against Trump ally Steve Bannon"
    },
    {
      "link": "https://apple.news/ARRNI6j_OQ9iUAF8meaL_lw",
      "rank": 5,
      "section": "top",
      "run_time": "2026-04-06 13:20:15",
      "pub_time": "",
      "publication": "The Washington Post",
      "author": "",
      "headline": "Strongest El Niño in a century? What this rare phenomenon could bring.",
      "article_headline": "Strongest El Niño in a century? What this rare phenomenon could bring."
    },
    {
      "link": "https://apple.news/AmHm8fc7iTlOPxhP3ObLJZw",
      "rank": 6,
      "section": "top",
      "run_time": "2026-04-06 13:20:15",
      "pub_time": "2026-04-06 13:16:46",
      "publication": "KFF Health News",
      "author": "Vanessa G. Sánchez, El Tímpano",
      "headline": "Older immigrants lose Medicare coverage even though they pay for it",
      "article_headline": "Older immigrants lose Medicare coverage even though they pay for it"
    },
    {
      "link": "",
      "rank": "plus",
      "section": "top",
      "run_time": "2026-04-06 13:20:15",
      "pub_time": "2026-04-06 13:17:13",
      "publication": "WIRED",
      "author": "David Gilbert",
      "headline": "The new era of militia influencers",
      "article_headline": ""
    }
  ]
}