{
  "run_time": "2026-03-24 15:20:13",
  "story_count": 7,
  "stories": [
    {
      "link": "https://apple.news/AfA368EBPQ1yvrU3Q13Kk3A",
      "rank": 1,
      "section": "top",
      "run_time": "2026-03-24 15:20:13",
      "pub_time": "",
      "publication": "The Associated Press",
      "headline": "Airport disruptions abound as senators chase deal to end Homeland Security budget standoff",
      "article_headline": "Airport disruptions abound as senators chase deal to end Homeland Security budget standoff"
    },
    {
      "link": "https://apple.news/ANVP-mYQISKS3yrPDS9aETQ",
      "rank": 2,
      "section": "top",
      "run_time": "2026-03-24 15:20:13",
      "pub_time": "2026-03-24 14:54:42",
      "publication": "POLITICO",
      "headline": "Pentagon prepares to send another 3,000 troops to Middle East",
      "article_headline": "Pentagon prepares to send another 3,000 troops to Middle East"
    },
    {
      "link": "https://apple.news/AvsHyn8vHTvmUXvxYWs47Tw",
      "rank": 3,
      "section": "top",
      "run_time": "2026-03-24 15:20:13",
      "pub_time": "2026-03-24 14:55:10",
      "publication": "ABC News",
      "headline": "Runway safety system “did not alert” in deadly LaGuardia Airport collision, NTSB says",
      "article_headline": "Runway safety system “did not alert” in deadly LaGuardia Airport collision, NTSB says"
    },
    {
      "link": "https://apple.news/ANVP-mYQISKS3yrPDS9aETQ",
      "rank": 4,
      "section": "top",
      "run_time": "2026-03-24 15:20:13",
      "pub_time": "2026-03-24 14:54:43",
      "publication": "POLITICO",
      "headline": "Pentagon prepares to send another 3,000 troops to Middle East",
      "article_headline": "Pentagon prepares to send another 3,000 troops to Middle East"
    },
    {
      "link": "https://apple.news/AvsHyn8vHTvmUXvxYWs47Tw",
      "rank": 5,
      "section": "top",
      "run_time": "2026-03-24 15:20:13",
      "pub_time": "2026-03-24 14:55:10",
      "publication": "ABC News",
      "headline": "Runway safety system “did not alert” in deadly LaGuardia Airport collision, NTSB says",
      "article_headline": "Runway safety system “did not alert” in deadly LaGuardia Airport collision, NTSB says"
    },
    {
      "link": "https://apple.news/Ah4mEz-YESam1caE68iKOQQ",
      "rank": 6,
      "section": "top",
      "run_time": "2026-03-24 15:20:13",
      "pub_time": "2026-03-24 14:55:38",
      "publication": "The Minnesota Star Tribune",
      "headline": "Minnesota sues Trump administration for evidence in Good, Pretti killings",
      "article_headline": "Minnesota sues Trump administration for evidence in Good, Pretti killings"
    },
    {
      "link": "https://apple.news/Ah4mEz-YESam1caE68iKOQQ",
      "rank": 7,
      "section": "top",
      "run_time": "2026-03-24 15:20:13",
      "pub_time": "2026-03-24 14:55:10",
      "publication": "The Minnesota Star Tribune",
      "headline": "Minnesota sues Trump administration for evidence in Good, Pretti killings",
      "article_headline": "Minnesota sues Trump administration for evidence in Good, Pretti killings"
    }
  ]
}