{
  "run_time": "2026-03-12 18:40:13",
  "story_count": 21,
  "stories": [
    {
      "link": "https://apple.news/AxUHQvAjqSaasyE5B50Svmw",
      "rank": 1,
      "section": "top",
      "run_time": "2026-03-12 18:40:13",
      "pub_time": "2026-03-12 18:33:15",
      "publication": "Reuters",
      "headline": "Iran’s new supreme leader vows to keep Hormuz shut as Netanyahu issues threat, MORE COVERAGE",
      "article_headline": "Iran’s new supreme leader vows to keep Hormuz shut as Netanyahu issues threat"
    },
    {
      "link": "https://apple.news/AHqdgQFZ7S6e6TPXzvsmLgg",
      "rank": 2,
      "section": "top",
      "run_time": "2026-03-12 18:40:13",
      "pub_time": "2026-03-12 18:33:47",
      "publication": "ABC News",
      "headline": "Michigan synagogue ramming probed as targeted act of violence against Jewish community, FBI says",
      "article_headline": "Michigan synagogue ramming probed as targeted act of violence against Jewish community, FBI says"
    },
    {
      "link": "https://apple.news/A6kyt3dB_QZGgyZJKhJbWfw",
      "rank": 3,
      "section": "top",
      "run_time": "2026-03-12 18:40:13",
      "pub_time": "2026-03-12 18:34:15",
      "publication": "WHRO Public Media",
      "headline": "FBI investigating deadly Old Dominion University shooting as a terrorist attack",
      "article_headline": "FBI confirms ODU shooter's identity, will investigate fatal campus shooting as a terrorist attack"
    },
    {
      "link": "https://apple.news/AHqdgQFZ7S6e6TPXzvsmLgg",
      "rank": 4,
      "section": "top",
      "run_time": "2026-03-12 18:40:13",
      "pub_time": "2026-03-12 18:33:48",
      "publication": "ABC News",
      "headline": "Michigan synagogue ramming probed as targeted act of violence against Jewish community, FBI says",
      "article_headline": "Michigan synagogue ramming probed as targeted act of violence against Jewish community, FBI says"
    },
    {
      "link": "https://apple.news/A6kyt3dB_QZGgyZJKhJbWfw",
      "rank": 5,
      "section": "top",
      "run_time": "2026-03-12 18:40:13",
      "pub_time": "2026-03-12 18:34:16",
      "publication": "WHRO Public Media",
      "headline": "FBI investigating deadly Old Dominion University shooting as a terrorist attack",
      "article_headline": "FBI confirms ODU shooter's identity, will investigate fatal campus shooting as a terrorist attack"
    },
    {
      "link": "",
      "rank": "plus",
      "section": "top",
      "run_time": "2026-03-12 18:40:13",
      "pub_time": "2026-03-12 18:34:43",
      "publication": "The Minnesota Star Tribune",
      "headline": "Fast-tracked asylum hearings for Somali refugees being held in secret",
      "article_headline": ""
    },
    {
      "link": "",
      "rank": "plus",
      "section": "top",
      "run_time": "2026-03-12 18:40:13",
      "pub_time": "2026-03-12 18:34:02",
      "publication": "The Minnesota Star Tribune",
      "headline": "Fast-tracked asylum hearings for Somali refugees being held in secret",
      "article_headline": ""
    },
    {
      "link": "",
      "rank": "plus",
      "section": "top",
      "run_time": "2026-03-12 18:40:13",
      "pub_time": "",
      "publication": "Vox",
      "headline": "The elder-care solution that could transform a generation, Audio, 1 min",
      "article_headline": ""
    },
    {
      "link": "",
      "rank": "plus",
      "section": "top",
      "run_time": "2026-03-12 18:40:13",
      "pub_time": "2026-03-11 18:43:48",
      "publication": "Vanity Fair",
      "headline": "Kylie Supreme! A Makeup Mogul Enters Her Hollywood Era",
      "article_headline": ""
    },
    {
      "link": "",
      "rank": "plus",
      "section": "top",
      "run_time": "2026-03-12 18:40:13",
      "pub_time": "2026-03-12 18:17:00",
      "publication": "Billboard",
      "headline": "Taylor Swift Fans in Vancouver May Receive Refunds for Undisclosed 'Obstructed View' Eras Tour Tickets",
      "article_headline": ""
    },
    {
      "link": "",
      "rank": "plus",
      "section": "top",
      "run_time": "2026-03-12 18:40:13",
      "pub_time": "2026-03-12 18:25:16",
      "publication": "InStyle",
      "headline": "Dakota Johnson Is Reportedly \"Playing the Field\" Months After Breaking Up With Chris Martin",
      "article_headline": ""
    },
    {
      "link": "",
      "rank": "plus",
      "section": "top",
      "run_time": "2026-03-12 18:40:13",
      "pub_time": "2026-02-26 18:44:35",
      "publication": "Apple News Plus",
      "headline": "National Geographic, What you’ve been told about eggs and cholesterol is wrong",
      "article_headline": ""
    },
    {
      "link": "",
      "rank": "plus",
      "section": "top",
      "run_time": "2026-03-12 18:40:13",
      "pub_time": "",
      "publication": "Sports Illustrated",
      "headline": "Why college hoops is broken if Miami (Ohio) misses the men’s NCAA tournament",
      "article_headline": ""
    },
    {
      "link": "",
      "rank": "plus",
      "section": "top",
      "run_time": "2026-03-12 18:40:13",
      "pub_time": "",
      "publication": "Apple News Plus",
      "headline": "People, Conan O’Brien Reveals Friend Rob Reiner Will Receive ‘a Very Powerful’ Tribute During the 2026 Oscars, Ingrid Vasquez",
      "article_headline": ""
    },
    {
      "link": "",
      "rank": "plus",
      "section": "top",
      "run_time": "2026-03-12 18:40:13",
      "pub_time": "",
      "publication": "The Wall Street Journal",
      "headline": "‘Sesame Street’ Producer Sues SeaWorld Parent Over Unpaid Royalties, Jacob Passy",
      "article_headline": ""
    },
    {
      "link": "",
      "rank": "plus",
      "section": "top",
      "run_time": "2026-03-12 18:40:13",
      "pub_time": "",
      "publication": "People",
      "headline": "Gabourey Sidibe and Brandon Frankel Celebrate 5 Years of Marriage, Madison E. Goldberg",
      "article_headline": ""
    },
    {
      "link": "",
      "rank": "plus",
      "section": "top",
      "run_time": "2026-03-12 18:40:13",
      "pub_time": "",
      "publication": "Car and Driver",
      "headline": "2026 Buyer's Guide to Large Luxury SUVs",
      "article_headline": ""
    },
    {
      "link": "",
      "rank": "plus",
      "section": "top",
      "run_time": "2026-03-12 18:40:13",
      "pub_time": "",
      "publication": "Texas Monthly",
      "headline": "The 10 Best New Restaurants in Texas, Paula Forbes",
      "article_headline": ""
    },
    {
      "link": "",
      "rank": "plus",
      "section": "top",
      "run_time": "2026-03-12 18:40:13",
      "pub_time": "2026-03-12 16:48:35",
      "publication": "ELLE",
      "headline": "Zendaya Channels Carrie Bradshaw—and Whitney Houston—in One Dress",
      "article_headline": ""
    },
    {
      "link": "",
      "rank": "plus",
      "section": "top",
      "run_time": "2026-03-12 18:40:13",
      "pub_time": "2026-03-12 17:54:54",
      "publication": "Apple News Plus",
      "headline": "Real Simple, What Happens to Your Brain When You Don’t Eat Enough Healthy Fats",
      "article_headline": ""
    },
    {
      "link": "",
      "rank": "plus",
      "section": "top",
      "run_time": "2026-03-12 18:40:13",
      "pub_time": "",
      "publication": "Apple News Plus",
      "headline": "WIRED, How to Responsibly Dispose of Your Electronics, Simon Hill",
      "article_headline": ""
    }
  ]
}