{
  "run_time": "2026-04-27 03:00:16",
  "story_count": 11,
  "stories": [
    {
      "link": "https://apple.news/AmvbW7aSVTmmej8FfDyUK1A",
      "rank": 1,
      "section": "top",
      "run_time": "2026-04-27 03:00:16",
      "pub_time": "2026-04-27 00:00:18",
      "publication": "The Associated Press",
      "author": "",
      "headline": "White House Correspondents’ dinner shooting suspect aired grievances against Trump in writings to family, MORE DETAILS",
      "article_headline": "White House Correspondents’ dinner shooting suspect aired grievances against Trump in writings to family"
    },
    {
      "link": "https://apple.news/AoO7vFnj1SLmgJdj25nzvKA",
      "rank": 2,
      "section": "top",
      "run_time": "2026-04-27 03:00:16",
      "pub_time": "2026-04-27 00:00:49",
      "publication": "Reuters",
      "author": "",
      "headline": "Israeli strikes kill 14 in Lebanon as Israel warns residents to leave towns beyond “buffer zone”",
      "article_headline": "Israeli strikes kill 14 in Lebanon as Israel warns residents to leave towns beyond “buffer zone”"
    },
    {
      "link": "https://apple.news/A9lvz82bFRvmIsA9stVlBcQ",
      "rank": 3,
      "section": "top",
      "run_time": "2026-04-27 03:00:16",
      "pub_time": "2026-04-27 00:01:16",
      "publication": "Barron’s",
      "author": "Nicole Goodkind",
      "headline": "The last major obstacle to Warsh’s confirmation as Fed chair has finally been removed",
      "article_headline": "The last major obstacle to Warsh’s confirmation as Fed chair has finally been removed"
    },
    {
      "link": "",
      "rank": "plus",
      "section": "top",
      "run_time": "2026-04-27 03:00:16",
      "pub_time": "2026-04-27 00:01:49",
      "publication": "The Wall Street Journal",
      "author": "Max Colchester",
      "headline": "King Charles is on a mission to salvage U.K. relations with Trump",
      "article_headline": "",
      "link_status": "P"
    },
    {
      "link": "https://apple.news/Ae6TSjTGsSRm1MSRpfLGMqw",
      "rank": 4,
      "section": "top",
      "run_time": "2026-04-27 03:00:16",
      "pub_time": "2026-04-27 00:01:49",
      "publication": "The Washington Post",
      "author": "Tim Craig",
      "headline": "A town of 7,000 planned so many data centers, it’s like adding 51 Walmarts",
      "article_headline": "A town of 7,000 planned so many data centers, it’s like adding 51 Walmarts"
    },
    {
      "link": "",
      "rank": "plus",
      "section": "top",
      "run_time": "2026-04-27 03:00:16",
      "pub_time": "2026-04-27 00:02:23",
      "publication": "Bloomberg Businessweek",
      "author": "Mary Schlangenstein and Devin Leonard",
      "headline": "United’s CEO has a plan to build the “unequivocal best airline in history”",
      "article_headline": "",
      "link_status": "P"
    },
    {
      "link": "https://apple.news/A7iQDC32fRkKEES-eCC0W2w",
      "rank": 1,
      "section": "trending",
      "run_time": "2026-04-27 03:00:16",
      "pub_time": "2026-04-26 17:02:29",
      "publication": "TheStreet",
      "author": "Hillary Remy and Celine Provini",
      "headline": "Warren Buffett has stark message for investors on stock market",
      "article_headline": "Warren Buffett has stark message for investors on stock market"
    },
    {
      "link": "https://apple.news/AONG_mQx5TtuizqNlnwwWhQ",
      "rank": 2,
      "section": "trending",
      "run_time": "2026-04-27 03:00:16",
      "pub_time": "2026-04-26 08:02:56",
      "publication": "BuzzFeed",
      "author": "Daniella Flores",
      "headline": "\"$150,000 A Year With An Annual Bonus\": 31 Jobs That Pay Really Well For Surprisingly Little Effort, According To The People Who Have Them",
      "article_headline": "\"$150,000 A Year With An Annual Bonus\": 31 Jobs That Pay Really Well For Surprisingly Little Effort, According To The People Who Have Them"
    },
    {
      "link": "",
      "rank": 3,
      "section": "trending",
      "run_time": "2026-04-27 03:00:16",
      "pub_time": "2026-04-26 06:03:23",
      "publication": "",
      "author": "Olivia Bria",
      "headline": "After Using This Water Pitcher That Filters Out Forever Chemicals, I’ll Never Go Back to a Brita",
      "article_headline": "",
      "link_status": "P"
    },
    {
      "link": "https://apple.news/AnDg7dVtVT62QjwzV6Pb_Ag",
      "rank": 4,
      "section": "trending",
      "run_time": "2026-04-27 03:00:16",
      "pub_time": "2026-04-26 07:03:30",
      "publication": "San Francisco Chronicle",
      "author": "",
      "headline": "Not ready for a caregiver, this Bay Area couple found another way to age at home",
      "article_headline": "Not ready for a caregiver, this Bay Area couple found another way to age at home"
    },
    {
      "link": "",
      "rank": "plus",
      "section": "top",
      "run_time": "2026-04-27 03:00:16",
      "pub_time": "2026-04-27 02:04:25",
      "publication": "Apple News Plus",
      "author": "Seema Mehta",
      "headline": "Los Angeles Times, Billionaire-tax backers say they have enough signatures — times two — to qualify for ballot",
      "article_headline": "",
      "link_status": "P"
    }
  ]
}