{
  "run_time": "2026-04-17 06:20:17",
  "story_count": 7,
  "stories": [
    {
      "link": "https://apple.news/ARVyhkavvT4yzyAj64m3UVg",
      "rank": 1,
      "section": "top",
      "run_time": "2026-04-17 06:20:17",
      "pub_time": "2026-04-17 05:20:19",
      "publication": "The Associated Press",
      "author": "",
      "headline": "A 10-day ceasefire in Lebanon goes into effect and appears to hold",
      "article_headline": "A 10-day ceasefire in Lebanon goes into effect"
    },
    {
      "link": "https://apple.news/AqEKhEfhrQrax9bYKoA-BIg",
      "rank": 2,
      "section": "top",
      "run_time": "2026-04-17 06:20:17",
      "pub_time": "",
      "publication": "The Washington Post",
      "author": "",
      "headline": "Acting ICE chief Todd Lyons resigns, a year into Trump’s deportation campaign",
      "article_headline": "Acting ICE chief Todd Lyons resigns, a year into Trump’s deportation campaign"
    },
    {
      "link": "https://apple.news/A0YL_sDp2SdiV21_a0CBZfQ",
      "rank": 3,
      "section": "top",
      "run_time": "2026-04-17 06:20:17",
      "pub_time": "2026-04-17 05:21:18",
      "publication": "NBC News",
      "author": "Raquel Coronell Uribe and Eleanor Skelly",
      "headline": "Trump’s plan for a triumphal arch gets initial green light from federal panel",
      "article_headline": "Trump’s plan for a triumphal arch gets initial green light from federal panel"
    },
    {
      "link": "https://apple.news/A4x84-95dTrq4jtt9eZNMAQ",
      "rank": 4,
      "section": "top",
      "run_time": "2026-04-17 06:20:17",
      "pub_time": "2026-04-17 05:21:46",
      "publication": "POLITICO",
      "author": "Mia McCarthy, Meredith Lee Hill, and Jordain Carney",
      "headline": "House punts spy-powers fight for 2 weeks after GOP revolt",
      "article_headline": "House punts spy-powers fight for 2 weeks after GOP revolt"
    },
    {
      "link": "https://apple.news/AyKaswzLfRsyUxeTVv_t5YQ",
      "rank": 5,
      "section": "top",
      "run_time": "2026-04-17 06:20:17",
      "pub_time": "2026-04-17 05:22:19",
      "publication": "USA TODAY",
      "author": "",
      "headline": "A Grand Canyon mystery may have just been solved",
      "article_headline": "A Grand Canyon mystery may have just been solved"
    },
    {
      "link": "",
      "rank": "plus",
      "section": "top",
      "run_time": "2026-04-17 06:20:17",
      "pub_time": "2026-04-17 05:22:47",
      "publication": "The Wall Street Journal",
      "author": "Douglas Belkin",
      "headline": "Why everyone hates the Ivy League",
      "article_headline": "",
      "link_status": "P"
    },
    {
      "link": "https://apple.news/AyqPq9HjlSSKqhlcldmNzxA",
      "rank": 6,
      "section": "top",
      "run_time": "2026-04-17 06:20:17",
      "pub_time": "2026-04-17 04:23:18",
      "publication": "Inc.",
      "author": "REUT HACKMON",
      "headline": "Cybersecurity Experts Warn: This Common Email Habit Is a Gift to Hackers",
      "article_headline": "Cybersecurity Experts Warn: This Common Email Habit Is a Gift to Hackers"
    }
  ]
}