{
  "run_time": "2026-03-30 23:40:13",
  "story_count": 7,
  "stories": [
    {
      "link": "https://apple.news/AB4Y476iRTPqeKd7Obr9HsQ",
      "rank": 1,
      "section": "top",
      "run_time": "2026-03-30 23:40:13",
      "pub_time": "2026-03-30 22:52:14",
      "publication": "Reuters",
      "author": "Alexander Cornwell, Trevor Hunnicutt, and Yomna Ehab",
      "headline": "Iran strikes oil tanker off Dubai as Trump threatens to obliterate Iran energy, oil plants",
      "article_headline": "Giant oil tanker off Dubai hit by Iranian strike, Trump threatens to obliterate Iran energy, oil plants"
    },
    {
      "link": "https://apple.news/Anh9_XyS3RZSaJRDXIY_3jw",
      "rank": 2,
      "section": "top",
      "run_time": "2026-03-30 23:40:13",
      "pub_time": "2026-03-30 22:52:42",
      "publication": "The Guardian",
      "author": "Roque Planas",
      "headline": "Mexican immigrant dies in detention center, marking 14 deaths in ICE custody in 2026",
      "article_headline": "Mexican immigrant dies in detention center, marking 14 deaths in ICE custody in 2026"
    },
    {
      "link": "https://apple.news/Anh9_XyS3RZSaJRDXIY_3jw",
      "rank": 3,
      "section": "top",
      "run_time": "2026-03-30 23:40:13",
      "pub_time": "2026-03-30 22:52:19",
      "publication": "The Guardian",
      "author": "Roque Planas",
      "headline": "Mexican immigrant dies in detention center, marking 14 deaths in ICE custody in 2026",
      "article_headline": "Mexican immigrant dies in detention center, marking 14 deaths in ICE custody in 2026"
    },
    {
      "link": "https://apple.news/Ai3q1fp1lS0CpVzE_hnDWqw",
      "rank": 4,
      "section": "top",
      "run_time": "2026-03-30 23:40:13",
      "pub_time": "2026-03-30 22:52:47",
      "publication": "Video",
      "author": "Nicole Sganga and Kris Van Cleave",
      "headline": "CBS News, TSA absences still high at some airports, even as workers begin to get back pay",
      "article_headline": "TSA absences still high at some airports, even as workers begin to get back pay"
    },
    {
      "link": "https://apple.news/A1nvsPznVQ7eeKPWfotdNng",
      "rank": 5,
      "section": "top",
      "run_time": "2026-03-30 23:40:13",
      "pub_time": "2026-03-30 22:53:14",
      "publication": "The Associated Press",
      "author": "",
      "headline": "Trump administration sues Minnesota over transgender athletes in girls sports",
      "article_headline": "Trump administration sues Minnesota over transgender athletes in girls sports"
    },
    {
      "link": "https://apple.news/A1nvsPznVQ7eeKPWfotdNng",
      "rank": 6,
      "section": "top",
      "run_time": "2026-03-30 23:40:13",
      "pub_time": "2026-03-30 22:52:46",
      "publication": "The Associated Press",
      "author": "",
      "headline": "Trump administration sues Minnesota over transgender athletes in girls sports",
      "article_headline": "Trump administration sues Minnesota over transgender athletes in girls sports"
    },
    {
      "link": "https://apple.news/A-JofTbj6RUusvx55rLXJKQ",
      "rank": 7,
      "section": "top",
      "run_time": "2026-03-30 23:40:13",
      "pub_time": "2026-03-30 22:53:14",
      "publication": "NPR",
      "author": "Nell Greenfieldboyce",
      "headline": "NASA is just days away from historic Artemis II moon launch",
      "article_headline": "NASA is just days away from historic Artemis II moon launch"
    }
  ]
}